LICENSE.txt
MANIFEST.in
README.rst
setup.py
utility_helper.egg-info/PKG-INFO
utility_helper.egg-info/SOURCES.txt
utility_helper.egg-info/dependency_links.txt
utility_helper.egg-info/top_level.txt
utilityhelper/HelperConfigParser.py
utilityhelper/HelperMultiThread.py
utilityhelper/LogUtil.py
utilityhelper/__init__.py
utilityhelper/loggingHelper.py
utilityhelper/common/HelperDecorator.py
utilityhelper/common/HelperMagic.py
utilityhelper/common/__init__.py
utilityhelper/common/util/BasicUtil.py
utilityhelper/common/util/DBUtil.py
utilityhelper/common/util/DESUtil.py
utilityhelper/common/util/__init__.py
utilityhelper/common/util/CertUil/Codeutil.py
utilityhelper/common/util/CertUil/__init__.py
utilityhelper/common/util/CertUil/cert.py
utilityhelper/common/util/crc/__init__.py
utilityhelper/common/util/crc/crc-itu.py
utilityhelper/wxext/HelperButton.py
utilityhelper/wxext/HelperPieCtrl.py
utilityhelper/wxext/HelperPropertyGrid.py
utilityhelper/wxext/HelperToasterBox.py
utilityhelper/wxext/HelperTreeCtrl.py
utilityhelper/wxext/HelperValidator.py
utilityhelper/wxext/__init__.py
utilityhelper/wxext/myGrid.py
utilityhelper/wxext/myGridTable.py