Metadata-Version: 1.1
Name: utility-helper
Version: 0.1.2
Summary: some usefull wrapper class,function etc.
Home-page: UNKNOWN
Author: Leo Gong
Author-email: gongleilei@brilliance.com.cn
License: MIT
Keywords: python helper util
Platform: UNKNOWN
Classifier: Environment :: Plugins
Classifier: Intended Audience :: Developers
Classifier: Operating System :: OS Independent
Classifier: Topic :: Utilities
Classifier: Topic :: Software Development :: Libraries :: Python Modules
Classifier: Programming Language :: Python
Classifier: Programming Language :: Python :: 2
Classifier: Programming Language :: Python :: 2.6
Classifier: Programming Language :: Python :: 2.7
